idms_pairfinder_2
