Metadata-Version: 1.0
Name: idms-pairfinder-2
Version: 0.0.7
Summary: An APP for untargeted feature extraction from isotope dilution metabolomics data.
Home-page: UNKNOWN
Author: Patrick Kiefer
Author-email: pkiefer@ethz.ch
License: http://opensource.org/licenses/GPL-3.0
Platform: UNKNOWN
